{
  "title": "Dungeon Crawl Feed",
  "subtitle": "Floor Broadcast // Princess Donut Network",
  "footer": "Dungeon management denies responsibility for curses, lava, celebrity felines, emotional damage, or surprise quests.",
  "mode": "quest",
  "headline": "Bonus Objective",
  "quest_name": "Feed Mongo Properly",
  "difficulty": "Urgent",
  "objective": "Acquire acceptable monster-grade snacks before Mongo samples the locals.",
  "reward": "1500 XP, pet approval, reduced chaos",
  "warning": "Substitutions will be judged harshly."
}